lemonmeringue/__init__.py
lemonmeringue/client.py
lemonmeringue-0.1.4.dist-info/METADATA
lemonmeringue-0.1.4.dist-info/WHEEL
lemonmeringue-0.1.4.dist-info/entry_points.txt
lemonmeringue-0.1.4.dist-info/top_level.txt
lemonmeringue-0.1.4.dist-info/RECORD
