Metadata-Version: 2.1
Name: lemonmeringue
Version: 0.1.4
Summary: Enhanced Python SDK for LemonSlice API with retry logic and better error handling
Home-page: https://github.com/neeldatta/lemonmeringue
Author: Neel Datta
Author-email: neeldatta@berkeley.edu
Project-URL: Bug Reports, https://github.com/neeldatta/lemonmeringue/issues
Project-URL: Source, https://github.com/neeldatta/lemonmeringue
Project-URL: Documentation, https://github.com/neeldatta/lemonmeringue#readme
Keywords: lemonslice api video generation ai lip-sync sdk wrapper
Classifier: Development Status :: 3 - Alpha
Classifier: Intended Audience :: Developers
Classifier: Topic :: Software Development :: Libraries :: Python Modules
Classifier: Topic :: Internet :: WWW/HTTP :: Dynamic Content
Classifier: Topic :: Multimedia :: Video :: Display
Classifier: License :: OSI Approved :: MIT License
Classifier: Operating System :: OS Independent
Classifier: Programming Language :: Python :: 3
Classifier: Programming Language :: Python :: 3.8
Classifier: Programming Language :: Python :: 3.9
Classifier: Programming Language :: Python :: 3.10
Classifier: Programming Language :: Python :: 3.11
Classifier: Programming Language :: Python :: 3.12
Requires-Python: >=3.8
Requires-Dist: aiohttp >=3.8.0
Requires-Dist: pydantic <2.0.0,>=1.10.0
Requires-Dist: backoff >=2.2.0
Provides-Extra: dev
Requires-Dist: pytest >=7.0 ; extra == 'dev'
Requires-Dist: pytest-asyncio >=0.21.0 ; extra == 'dev'
Requires-Dist: pytest-cov >=4.0 ; extra == 'dev'
Requires-Dist: black >=22.0 ; extra == 'dev'
Requires-Dist: isort >=5.0 ; extra == 'dev'
Requires-Dist: flake8 >=5.0 ; extra == 'dev'
Requires-Dist: mypy >=1.0 ; extra == 'dev'
Requires-Dist: twine >=4.0 ; extra == 'dev'
Requires-Dist: build >=0.10 ; extra == 'dev'
